luna_viz/__init__.py
luna_viz/tpx3data.py
luna_viz/tpx3plot.py
luna_viz-0.0.1.dist-info/METADATA
luna_viz-0.0.1.dist-info/WHEEL
luna_viz-0.0.1.dist-info/entry_points.txt
luna_viz-0.0.1.dist-info/top_level.txt
luna_viz-0.0.1.dist-info/RECORD
